nosql2django/__init__.py
nosql2django/parser_mapper.py
nosql2django/tests/__init__.py
nosql2django/tests/models.py
nosql2django/tests/tests.py
nosql2django-0.1.1.dist-info/DESCRIPTION.rst
nosql2django-0.1.1.dist-info/METADATA
nosql2django-0.1.1.dist-info/RECORD
nosql2django-0.1.1.dist-info/WHEEL
nosql2django-0.1.1.dist-info/metadata.json
nosql2django-0.1.1.dist-info/top_level.txt
