Metadata-Version: 2.0
Name: nosql2django
Version: 0.1.1
Summary: Allow convert nosql source to django relational DB structure
Home-page: https://github.com/Akay7/nosql2django
Author: Egor Poderiagin
Author-email: egor@crazyrussian.pro
License: UNKNOWN
Keywords: django rss atom feeds parser sql nosql-to-sql
Platform: UNKNOWN
Classifier: Development Status :: 3 - Alpha
Classifier: Framework :: Django
Classifier: Intended Audience :: Developers
Classifier: Intended Audience :: System Administrators
Classifier: Operating System :: OS Independent
Classifier: Topic :: Software Development
Classifier: Programming Language :: Python :: 3
Classifier: Programming Language :: Python :: 3.4
Classifier: Programming Language :: Python :: 3.5
Requires-Dist: Django (>=1.8.0)
Requires-Dist: feedparser (>=5.2.1)
Requires-Dist: python-dateutil (>=2.6.0)
